{
  "date": "2026-07-24",
  "data": [
    {
      "lastYearRptDt": "7/18/2025",
      "lastYearEPS": "$4.08",
      "time": "time-pre-market",
      "symbol": "AXP",
      "name": "American Express Company",
      "marketCap": "$233,669,513,670",
      "fiscalQuarterEnding": "Jun/2026",
      "epsForecast": "$4.39",
      "noOfEsts": "7"
    },
    {
      "lastYearRptDt": "7/21/2025",
      "lastYearEPS": "$1.22",
      "time": "time-pre-market",
      "symbol": "VZ",
      "name": "Verizon Communications Inc.",
      "marketCap": "$192,367,998,984",
      "fiscalQuarterEnding": "Jun/2026",
      "epsForecast": "$1.27",
      "noOfEsts": "8"
    },
    {
      "lastYearRptDt": "7/25/2025",
      "lastYearEPS": "$6.84",
      "time": "time-not-supplied",
      "symbol": "HCA",
      "name": "HCA Healthcare, Inc.",
      "marketCap": "$85,838,692,212",
      "fiscalQuarterEnding": "Jun/2026",
      "epsForecast": "$7.37",
      "noOfEsts": "10"
    },
    {
      "lastYearRptDt": "7/25/2025",
      "lastYearEPS": "$0.79",
      "time": "time-not-supplied",
      "symbol": "E",
      "name": "ENI S.p.A.",
      "marketCap": "$73,618,569,842",
      "fiscalQuarterEnding": "Jun/2026",
      "epsForecast": "$1.92",
      "noOfEsts": "2"
    },
    {
      "lastYearRptDt": "7/22/2025",
      "lastYearEPS": "$1.35",
      "time": "time-pre-market",
      "symbol": "CNI",
      "name": "Canadian National Railway Company",
      "marketCap": "$72,907,883,988",
      "fiscalQuarterEnding": "Jun/2026",
      "epsForecast": "$1.40",
      "noOfEsts": "8"
    },
    {
      "lastYearRptDt": "7/18/2025",
      "lastYearEPS": "$0.74",
      "time": "time-pre-market",
      "symbol": "SLB",
      "name": "SLB Limited",
      "marketCap": "$70,895,634,285",
      "fiscalQuarterEnding": "Jun/2026",
      "epsForecast": "$0.52",
      "noOfEsts": "9"
    },
    {
      "lastYearRptDt": "7/25/2025",
      "lastYearEPS": "$0.41",
      "time": "time-not-supplied",
      "symbol": "NWG",
      "name": "NatWest Group plc",
      "marketCap": "$70,070,869,318",
      "fiscalQuarterEnding": "Jun/2026",
      "epsForecast": "$0.47",
      "noOfEsts": "1"
    },
    {
      "lastYearRptDt": "7/25/2025",
      "lastYearEPS": "$3.49",
      "time": "time-not-supplied",
      "symbol": "AON",
      "name": "Aon plc",
      "marketCap": "$67,479,637,037",
      "fiscalQuarterEnding": "Jun/2026",
      "epsForecast": "$3.77",
      "noOfEsts": "9"
    },
    {
      "lastYearRptDt": "7/25/2025",
      "lastYearEPS": "$4.27",
      "time": "time-not-supplied",
      "symbol": "SHG",
      "name": "Shinhan Financial Group Co Ltd",
      "marketCap": "$29,578,987,164",
      "fiscalQuarterEnding": "Jun/2026",
      "epsForecast": "$2.29",
      "noOfEsts": "2"
    },
    {
      "lastYearRptDt": "7/25/2025",
      "lastYearEPS": "$44.78",
      "time": "time-not-supplied",
      "symbol": "FCNCA",
      "name": "First Citizens BancShares, Inc.",
      "marketCap": "$24,207,621,951",
      "fiscalQuarterEnding": "Jun/2026",
      "epsForecast": "$39.94",
      "noOfEsts": "4"
    },
    {
      "lastYearRptDt": "7/25/2025",
      "lastYearEPS": "$9.18",
      "time": "time-not-supplied",
      "symbol": "CHTR",
      "name": "Charter Communications, Inc.",
      "marketCap": "$18,019,345,222",
      "fiscalQuarterEnding": "Jun/2026",
      "epsForecast": "$10.33",
      "noOfEsts": "7"
    },
    {
      "lastYearRptDt": "7/22/2025",
      "lastYearEPS": "$4.02",
      "time": "time-pre-market",
      "symbol": "THC",
      "name": "Tenet Healthcare Corporation",
      "marketCap": "$15,844,039,780",
      "fiscalQuarterEnding": "Jun/2026",
      "epsForecast": "$4.08",
      "noOfEsts": "7"
    },
    {
      "lastYearRptDt": "7/25/2025",
      "lastYearEPS": "$2.63",
      "time": "time-not-supplied",
      "symbol": "WF",
      "name": "Woori Bank",
      "marketCap": "$13,977,462,774",
      "fiscalQuarterEnding": "Jun/2026",
      "epsForecast": "",
      "noOfEsts": "N/A"
    },
    {
      "lastYearRptDt": "7/25/2025",
      "lastYearEPS": "$2.37",
      "time": "time-not-supplied",
      "symbol": "MOG.A",
      "name": "Moog Inc.",
      "marketCap": "$13,188,180,761",
      "fiscalQuarterEnding": "Jun/2026",
      "epsForecast": "$2.59",
      "noOfEsts": "2"
    },
    {
      "lastYearRptDt": "N/A",
      "lastYearEPS": "$2.37",
      "time": "time-not-supplied",
      "symbol": "MOG.B",
      "name": "Moog Inc.",
      "marketCap": "$13,188,180,761",
      "fiscalQuarterEnding": "Jun/2026",
      "epsForecast": "",
      "noOfEsts": "1"
    },
    {
      "lastYearRptDt": "7/25/2025",
      "lastYearEPS": "$2.67",
      "time": "time-not-supplied",
      "symbol": "SAIA",
      "name": "Saia, Inc.",
      "marketCap": "$11,567,038,800",
      "fiscalQuarterEnding": "Jun/2026",
      "epsForecast": "$3.23",
      "noOfEsts": "6"
    },
    {
      "lastYearRptDt": "7/25/2025",
      "lastYearEPS": "$1.48",
      "time": "time-pre-market",
      "symbol": "BAH",
      "name": "Booz Allen Hamilton Holding Corporation",
      "marketCap": "$7,150,041,422",
      "fiscalQuarterEnding": "Jun/2026",
      "epsForecast": "$1.49",
      "noOfEsts": "5"
    },
    {
      "lastYearRptDt": "7/25/2025",
      "lastYearEPS": "$3.47",
      "time": "time-not-supplied",
      "symbol": "LEA",
      "name": "Lear Corporation",
      "marketCap": "$6,924,144,584",
      "fiscalQuarterEnding": "Jun/2026",
      "epsForecast": "$3.78",
      "noOfEsts": "5"
    },
    {
      "lastYearRptDt": "7/25/2025",
      "lastYearEPS": "$1.45",
      "time": "time-not-supplied",
      "symbol": "OMF",
      "name": "OneMain Holdings, Inc.",
      "marketCap": "$6,919,148,715",
      "fiscalQuarterEnding": "Jun/2026",
      "epsForecast": "$1.46",
      "noOfEsts": "5"
    },
    {
      "lastYearRptDt": "7/25/2025",
      "lastYearEPS": "$5.46",
      "time": "time-not-supplied",
      "symbol": "AN",
      "name": "AutoNation, Inc.",
      "marketCap": "$6,426,280,115",
      "fiscalQuarterEnding": "Jun/2026",
      "epsForecast": "$5.35",
      "noOfEsts": "6"
    },
    {
      "lastYearRptDt": "7/25/2025",
      "lastYearEPS": "($0.14)",
      "time": "time-not-supplied",
      "symbol": "FLG",
      "name": "Flagstar Bank, N.A.",
      "marketCap": "$6,314,749,098",
      "fiscalQuarterEnding": "Jun/2026",
      "epsForecast": "$0.07",
      "noOfEsts": "9"
    },
    {
      "lastYearRptDt": "7/23/2025",
      "lastYearEPS": "$0.87",
      "time": "time-pre-market",
      "symbol": "LW",
      "name": "Lamb Weston Holdings, Inc.",
      "marketCap": "$6,169,092,838",
      "fiscalQuarterEnding": "May/2026",
      "epsForecast": "$0.61",
      "noOfEsts": "5"
    },
    {
      "lastYearRptDt": "7/25/2025",
      "lastYearEPS": "$0.66",
      "time": "time-not-supplied",
      "symbol": "POR",
      "name": "Portland General Electric Company",
      "marketCap": "$5,971,668,568",
      "fiscalQuarterEnding": "Jun/2026",
      "epsForecast": "$0.71",
      "noOfEsts": "2"
    },
    {
      "lastYearRptDt": "7/25/2025",
      "lastYearEPS": "$0.47",
      "time": "time-not-supplied",
      "symbol": "GNTX",
      "name": "Gentex Corporation",
      "marketCap": "$5,505,692,184",
      "fiscalQuarterEnding": "Jun/2026",
      "epsForecast": "$0.49",
      "noOfEsts": "3"
    },
    {
      "lastYearRptDt": "7/25/2025",
      "lastYearEPS": "$0.94",
      "time": "time-pre-market",
      "symbol": "SXT",
      "name": "Sensient Technologies Corporation",
      "marketCap": "$5,185,750,707",
      "fiscalQuarterEnding": "Jun/2026",
      "epsForecast": "$1",
      "noOfEsts": "1"
    },
    {
      "lastYearRptDt": "8/01/2025",
      "lastYearEPS": "($8.09)",
      "time": "time-pre-market",
      "symbol": "LBTYA",
      "name": "Liberty Global Ltd.",
      "marketCap": "$3,597,346,749",
      "fiscalQuarterEnding": "Jun/2026",
      "epsForecast": "($0.31)",
      "noOfEsts": "1"
    },
    {
      "lastYearRptDt": "N/A",
      "lastYearEPS": "($8.09)",
      "time": "time-pre-market",
      "symbol": "LBTYB",
      "name": "Liberty Global Ltd.",
      "marketCap": "$3,597,346,749",
      "fiscalQuarterEnding": "Jun/2026",
      "epsForecast": "",
      "noOfEsts": "1"
    },
    {
      "lastYearRptDt": "N/A",
      "lastYearEPS": "($8.09)",
      "time": "time-pre-market",
      "symbol": "LBTYK",
      "name": "Liberty Global Ltd.",
      "marketCap": "$3,597,346,749",
      "fiscalQuarterEnding": "Jun/2026",
      "epsForecast": "",
      "noOfEsts": "1"
    },
    {
      "lastYearRptDt": "7/25/2025",
      "lastYearEPS": "$0.58",
      "time": "time-not-supplied",
      "symbol": "FHB",
      "name": "First Hawaiian, Inc.",
      "marketCap": "$3,564,314,909",
      "fiscalQuarterEnding": "Jun/2026",
      "epsForecast": "$0.58",
      "noOfEsts": "4"
    },
    {
      "lastYearRptDt": "N/A",
      "lastYearEPS": "N/A",
      "time": "time-not-supplied",
      "symbol": "PLBL",
      "name": "Polibeli Group Ltd",
      "marketCap": "$2,989,721,755",
      "fiscalQuarterEnding": "Mar/2026",
      "epsForecast": "",
      "noOfEsts": "1"
    },
    {
      "lastYearRptDt": "7/25/2025",
      "lastYearEPS": "$0.60",
      "time": "time-not-supplied",
      "symbol": "GRC",
      "name": "Gorman-Rupp Company (The)",
      "marketCap": "$2,399,370,577",
      "fiscalQuarterEnding": "Jun/2026",
      "epsForecast": "$0.69",
      "noOfEsts": "1"
    },
    {
      "lastYearRptDt": "7/25/2025",
      "lastYearEPS": "$0.87",
      "time": "time-not-supplied",
      "symbol": "TNET",
      "name": "TriNet Group, Inc.",
      "marketCap": "$2,170,884,382",
      "fiscalQuarterEnding": "Jun/2026",
      "epsForecast": "$0.72",
      "noOfEsts": "3"
    },
    {
      "lastYearRptDt": "7/25/2025",
      "lastYearEPS": "$0.51",
      "time": "time-not-supplied",
      "symbol": "STEL",
      "name": "Stellar Bancorp, Inc.",
      "marketCap": "$1,995,582,155",
      "fiscalQuarterEnding": "Jun/2026",
      "epsForecast": "$0.52",
      "noOfEsts": "1"
    },
    {
      "lastYearRptDt": "7/25/2025",
      "lastYearEPS": "$0.17",
      "time": "time-not-supplied",
      "symbol": "CRI",
      "name": "Carter's, Inc.",
      "marketCap": "$1,587,871,542",
      "fiscalQuarterEnding": "Jun/2026",
      "epsForecast": "$0.02",
      "noOfEsts": "2"
    },
    {
      "lastYearRptDt": "7/25/2025",
      "lastYearEPS": "$1.04",
      "time": "time-not-supplied",
      "symbol": "LKFN",
      "name": "Lakeland Financial Corporation",
      "marketCap": "$1,535,673,441",
      "fiscalQuarterEnding": "Jun/2026",
      "epsForecast": "$1.07",
      "noOfEsts": "1"
    },
    {
      "lastYearRptDt": "7/25/2025",
      "lastYearEPS": "$1.50",
      "time": "time-not-supplied",
      "symbol": "TMP",
      "name": "Tompkins Financial Corporation",
      "marketCap": "$1,341,928,395",
      "fiscalQuarterEnding": "Jun/2026",
      "epsForecast": "$1.80",
      "noOfEsts": "1"
    },
    {
      "lastYearRptDt": "7/25/2025",
      "lastYearEPS": "$0.72",
      "time": "time-not-supplied",
      "symbol": "SBSI",
      "name": "Southside Bancshares, Inc.",
      "marketCap": "$1,045,177,607",
      "fiscalQuarterEnding": "Jun/2026",
      "epsForecast": "$0.88",
      "noOfEsts": "2"
    },
    {
      "lastYearRptDt": "7/25/2025",
      "lastYearEPS": "$0.67",
      "time": "time-not-supplied",
      "symbol": "CPF",
      "name": "CPB Inc.",
      "marketCap": "$985,582,407",
      "fiscalQuarterEnding": "Jun/2026",
      "epsForecast": "$0.80",
      "noOfEsts": "2"
    },
    {
      "lastYearRptDt": "7/25/2025",
      "lastYearEPS": "$6.25",
      "time": "time-not-supplied",
      "symbol": "VRTS",
      "name": "Virtus Investment Partners, Inc.",
      "marketCap": "$906,697,134",
      "fiscalQuarterEnding": "Jun/2026",
      "epsForecast": "$5.95",
      "noOfEsts": "2"
    },
    {
      "lastYearRptDt": "7/25/2025",
      "lastYearEPS": "($0.15)",
      "time": "time-not-supplied",
      "symbol": "WNC",
      "name": "Wabash National Corporation",
      "marketCap": "$566,995,100",
      "fiscalQuarterEnding": "Jun/2026",
      "epsForecast": "($0.44)",
      "noOfEsts": "1"
    },
    {
      "lastYearRptDt": "7/25/2025",
      "lastYearEPS": "$0.91",
      "time": "time-not-supplied",
      "symbol": "COFS",
      "name": "ChoiceOne Financial Services, Inc.",
      "marketCap": "$490,731,897",
      "fiscalQuarterEnding": "Jun/2026",
      "epsForecast": "$0.87",
      "noOfEsts": "2"
    },
    {
      "lastYearRptDt": "7/25/2025",
      "lastYearEPS": "$0.25",
      "time": "time-not-supplied",
      "symbol": "PDLB",
      "name": "Ponce Financial Group, Inc.",
      "marketCap": "$472,873,465",
      "fiscalQuarterEnding": "Jun/2026",
      "epsForecast": "$0.37",
      "noOfEsts": "1"
    },
    {
      "lastYearRptDt": "N/A",
      "lastYearEPS": "($0.46)",
      "time": "time-not-supplied",
      "symbol": "PAMT",
      "name": "PAMT CORP",
      "marketCap": "$316,871,176",
      "fiscalQuarterEnding": "Jun/2026",
      "epsForecast": "",
      "noOfEsts": "1"
    },
    {
      "lastYearRptDt": "N/A",
      "lastYearEPS": "$1.13",
      "time": "time-not-supplied",
      "symbol": "FCAP",
      "name": "First Capital, Inc.",
      "marketCap": "$210,734,998",
      "fiscalQuarterEnding": "Jun/2026",
      "epsForecast": "",
      "noOfEsts": "1"
    },
    {
      "lastYearRptDt": "N/A",
      "lastYearEPS": "$0.89",
      "time": "time-not-supplied",
      "symbol": "OVBC",
      "name": "Ohio Valley Banc Corp.",
      "marketCap": "$199,934,882",
      "fiscalQuarterEnding": "Jun/2026",
      "epsForecast": "",
      "noOfEsts": "1"
    },
    {
      "lastYearRptDt": "7/25/2025",
      "lastYearEPS": "($1.60)",
      "time": "time-not-supplied",
      "symbol": "EAF",
      "name": "GrafTech International Ltd.",
      "marketCap": "$190,670,152",
      "fiscalQuarterEnding": "Jun/2026",
      "epsForecast": "($1.49)",
      "noOfEsts": "2"
    },
    {
      "lastYearRptDt": "N/A",
      "lastYearEPS": "$0.36",
      "time": "time-not-supplied",
      "symbol": "AFBI",
      "name": "Affinity Bancshares, Inc.",
      "marketCap": "$137,439,657",
      "fiscalQuarterEnding": "Jun/2026",
      "epsForecast": "",
      "noOfEsts": "1"
    },
    {
      "lastYearRptDt": "N/A",
      "lastYearEPS": "$0.73",
      "time": "time-not-supplied",
      "symbol": "AXR",
      "name": "AMREP Corporation",
      "marketCap": "$135,813,094",
      "fiscalQuarterEnding": "Apr/2026",
      "epsForecast": "",
      "noOfEsts": "1"
    },
    {
      "lastYearRptDt": "N/A",
      "lastYearEPS": "N/A",
      "time": "time-not-supplied",
      "symbol": "APLM",
      "name": "Apollomics Inc.",
      "marketCap": "$48,313,144",
      "fiscalQuarterEnding": "Mar/2026",
      "epsForecast": "",
      "noOfEsts": "1"
    },
    {
      "lastYearRptDt": "N/A",
      "lastYearEPS": "N/A",
      "time": "time-not-supplied",
      "symbol": "EBON",
      "name": "Ebang International Holdings Inc.",
      "marketCap": "$14,723,861",
      "fiscalQuarterEnding": "Mar/2026",
      "epsForecast": "",
      "noOfEsts": "1"
    },
    {
      "lastYearRptDt": "N/A",
      "lastYearEPS": "N/A",
      "time": "time-not-supplied",
      "symbol": "BGI",
      "name": "Birks Group Inc.",
      "marketCap": "$11,464,851",
      "fiscalQuarterEnding": "Mar/2026",
      "epsForecast": "",
      "noOfEsts": "1"
    },
    {
      "lastYearRptDt": "N/A",
      "lastYearEPS": "N/A",
      "time": "time-not-supplied",
      "symbol": "RAY",
      "name": "Raytech Holding Limited",
      "marketCap": "$7,956,650",
      "fiscalQuarterEnding": "Mar/2026",
      "epsForecast": "",
      "noOfEsts": "1"
    },
    {
      "lastYearRptDt": "N/A",
      "lastYearEPS": "N/A",
      "time": "time-not-supplied",
      "symbol": "ILAG",
      "name": "Intelligent Living Application Group Inc.",
      "marketCap": "$7,456,243",
      "fiscalQuarterEnding": "Mar/2026",
      "epsForecast": "",
      "noOfEsts": "1"
    },
    {
      "lastYearRptDt": "N/A",
      "lastYearEPS": "N/A",
      "time": "time-not-supplied",
      "symbol": "ALP",
      "name": "Alpha Compute Corp ",
      "marketCap": "$5,884,425",
      "fiscalQuarterEnding": "Mar/2026",
      "epsForecast": "($0.34)",
      "noOfEsts": "1"
    },
    {
      "lastYearRptDt": "N/A",
      "lastYearEPS": "N/A",
      "time": "time-not-supplied",
      "symbol": "CRE",
      "name": "Cre8 Enterprise Limited",
      "marketCap": "$5,478,039",
      "fiscalQuarterEnding": "Mar/2026",
      "epsForecast": "",
      "noOfEsts": "1"
    },
    {
      "lastYearRptDt": "N/A",
      "lastYearEPS": "N/A",
      "time": "time-not-supplied",
      "symbol": "HKIT",
      "name": "Hitek Global Inc.",
      "marketCap": "$2,014,676",
      "fiscalQuarterEnding": "Mar/2026",
      "epsForecast": "",
      "noOfEsts": "1"
    }
  ]
}