{
  "date": "2026-05-19",
  "data": [
    {
      "lastYearRptDt": "5/20/2025",
      "lastYearEPS": "$3.56",
      "time": "time-pre-market",
      "symbol": "HD",
      "name": "Home Depot, Inc. (The)",
      "marketCap": "$327,493,893,950",
      "fiscalQuarterEnding": "Apr/2026",
      "epsForecast": "$3.42",
      "noOfEsts": "12"
    },
    {
      "lastYearRptDt": "5/20/2025",
      "lastYearEPS": "$0.43",
      "time": "time-not-supplied",
      "symbol": "PANW",
      "name": "Palo Alto Networks, Inc.",
      "marketCap": "$146,325,120,000",
      "fiscalQuarterEnding": "Apr/2026",
      "epsForecast": "$0.43",
      "noOfEsts": "15"
    },
    {
      "lastYearRptDt": "5/20/2025",
      "lastYearEPS": "$1.49",
      "time": "time-after-hours",
      "symbol": "KEYS",
      "name": "Keysight Technologies Inc.",
      "marketCap": "$60,010,438,025",
      "fiscalQuarterEnding": "Apr/2026",
      "epsForecast": "$2.04",
      "noOfEsts": "2"
    },
    {
      "lastYearRptDt": "N/A",
      "lastYearEPS": "N/A",
      "time": "time-not-supplied",
      "symbol": "CCEP",
      "name": "Coca-Cola Europacific Partners plc",
      "marketCap": "$43,048,500,594",
      "fiscalQuarterEnding": "Mar/2026",
      "epsForecast": "",
      "noOfEsts": "1"
    },
    {
      "lastYearRptDt": "N/A",
      "lastYearEPS": "N/A",
      "time": "time-not-supplied",
      "symbol": "VOD",
      "name": "Vodafone Group Plc",
      "marketCap": "$36,694,202,529",
      "fiscalQuarterEnding": "Mar/2026",
      "epsForecast": "",
      "noOfEsts": "N/A"
    },
    {
      "lastYearRptDt": "5/20/2025",
      "lastYearEPS": "($0.24)",
      "time": "time-not-supplied",
      "symbol": "VIK",
      "name": "Viking Holdings Ltd",
      "marketCap": "$36,514,334,454",
      "fiscalQuarterEnding": "Mar/2026",
      "epsForecast": "($0.12)",
      "noOfEsts": "4"
    },
    {
      "lastYearRptDt": "5/20/2025",
      "lastYearEPS": "$0.34",
      "time": "time-after-hours",
      "symbol": "ZTO",
      "name": "ZTO Express (Cayman) Inc.",
      "marketCap": "$19,701,758,734",
      "fiscalQuarterEnding": "Mar/2026",
      "epsForecast": "",
      "noOfEsts": "N/A"
    },
    {
      "lastYearRptDt": "5/20/2025",
      "lastYearEPS": "$0.26",
      "time": "time-pre-market",
      "symbol": "AS",
      "name": "Amer Sports, Inc.",
      "marketCap": "$19,557,395,262",
      "fiscalQuarterEnding": "Mar/2026",
      "epsForecast": "$0.30",
      "noOfEsts": "5"
    },
    {
      "lastYearRptDt": "5/20/2025",
      "lastYearEPS": "$0.31",
      "time": "time-not-supplied",
      "symbol": "HTHT",
      "name": "H World Group Limited",
      "marketCap": "$15,880,530,013",
      "fiscalQuarterEnding": "Mar/2026",
      "epsForecast": "",
      "noOfEsts": "N/A"
    },
    {
      "lastYearRptDt": "5/20/2025",
      "lastYearEPS": "$3.50",
      "time": "time-after-hours",
      "symbol": "TOL",
      "name": "Toll Brothers, Inc.",
      "marketCap": "$13,461,652,980",
      "fiscalQuarterEnding": "Apr/2026",
      "epsForecast": "$2.57",
      "noOfEsts": "7"
    },
    {
      "lastYearRptDt": "5/20/2025",
      "lastYearEPS": "$1.12",
      "time": "time-not-supplied",
      "symbol": "MOD",
      "name": "Modine Manufacturing Company",
      "marketCap": "$13,426,944,692",
      "fiscalQuarterEnding": "Mar/2026",
      "epsForecast": "$1.51",
      "noOfEsts": "6"
    },
    {
      "lastYearRptDt": "5/20/2025",
      "lastYearEPS": "$0.36",
      "time": "time-after-hours",
      "symbol": "JHX",
      "name": "James Hardie Industries plc.",
      "marketCap": "$12,242,207,600",
      "fiscalQuarterEnding": "Mar/2026",
      "epsForecast": "$0.29",
      "noOfEsts": "4"
    },
    {
      "lastYearRptDt": "5/20/2025",
      "lastYearEPS": "$0.39",
      "time": "time-not-supplied",
      "symbol": "XP",
      "name": "XP Inc.",
      "marketCap": "$9,930,856,751",
      "fiscalQuarterEnding": "Mar/2026",
      "epsForecast": "$0.48",
      "noOfEsts": "3"
    },
    {
      "lastYearRptDt": "5/20/2025",
      "lastYearEPS": "$0.02",
      "time": "time-pre-market",
      "symbol": "BILI",
      "name": "Bilibili Inc.",
      "marketCap": "$9,178,218,943",
      "fiscalQuarterEnding": "Mar/2026",
      "epsForecast": "$0.08",
      "noOfEsts": "2"
    },
    {
      "lastYearRptDt": "5/20/2025",
      "lastYearEPS": "($0.14)",
      "time": "time-not-supplied",
      "symbol": "VSAT",
      "name": "ViaSat, Inc.",
      "marketCap": "$8,952,647,640",
      "fiscalQuarterEnding": "Mar/2026",
      "epsForecast": "$0.10",
      "noOfEsts": "3"
    },
    {
      "lastYearRptDt": "5/20/2025",
      "lastYearEPS": "$0.48",
      "time": "time-not-supplied",
      "symbol": "GDS",
      "name": "GDS Holdings Limited",
      "marketCap": "$8,471,965,478",
      "fiscalQuarterEnding": "Mar/2026",
      "epsForecast": "$1.06",
      "noOfEsts": "1"
    },
    {
      "lastYearRptDt": "5/20/2025",
      "lastYearEPS": "$0.52",
      "time": "time-not-supplied",
      "symbol": "VIPS",
      "name": "Vipshop Holdings Limited",
      "marketCap": "$6,911,093,071",
      "fiscalQuarterEnding": "Mar/2026",
      "epsForecast": "$0.60",
      "noOfEsts": "2"
    },
    {
      "lastYearRptDt": "5/20/2025",
      "lastYearEPS": "$2.08",
      "time": "time-pre-market",
      "symbol": "EXP",
      "name": "Eagle Materials Inc",
      "marketCap": "$6,604,206,515",
      "fiscalQuarterEnding": "Mar/2026",
      "epsForecast": "$1.47",
      "noOfEsts": "2"
    },
    {
      "lastYearRptDt": "N/A",
      "lastYearEPS": "$0.23",
      "time": "time-pre-market",
      "symbol": "CMBT",
      "name": "CMB.TECH NV",
      "marketCap": "$4,351,012,199",
      "fiscalQuarterEnding": "Mar/2026",
      "epsForecast": "",
      "noOfEsts": "1"
    },
    {
      "lastYearRptDt": "5/20/2025",
      "lastYearEPS": "($0.12)",
      "time": "time-not-supplied",
      "symbol": "PONY",
      "name": "Pony AI Inc.",
      "marketCap": "$4,279,055,128",
      "fiscalQuarterEnding": "Mar/2026",
      "epsForecast": "",
      "noOfEsts": "N/A"
    },
    {
      "lastYearRptDt": "5/26/2025",
      "lastYearEPS": "($0.02)",
      "time": "time-pre-market",
      "symbol": "HSAI",
      "name": "Hesai Group",
      "marketCap": "$3,548,060,085",
      "fiscalQuarterEnding": "Mar/2026",
      "epsForecast": "",
      "noOfEsts": "N/A"
    },
    {
      "lastYearRptDt": "N/A",
      "lastYearEPS": "$0.30",
      "time": "time-not-supplied",
      "symbol": "BWLP",
      "name": "BW LPG Limited",
      "marketCap": "$3,176,083,080",
      "fiscalQuarterEnding": "Mar/2026",
      "epsForecast": "",
      "noOfEsts": "1"
    },
    {
      "lastYearRptDt": "5/20/2025",
      "lastYearEPS": "$0.10",
      "time": "time-not-supplied",
      "symbol": "IHS",
      "name": "IHS Holding Limited",
      "marketCap": "$2,754,629,233",
      "fiscalQuarterEnding": "Mar/2026",
      "epsForecast": "$0.13",
      "noOfEsts": "1"
    },
    {
      "lastYearRptDt": "5/14/2025",
      "lastYearEPS": "($0.06)",
      "time": "time-pre-market",
      "symbol": "LUXE",
      "name": "LuxExperience B.V.",
      "marketCap": "$1,227,368,304",
      "fiscalQuarterEnding": "Mar/2026",
      "epsForecast": "($0.20)",
      "noOfEsts": "2"
    },
    {
      "lastYearRptDt": "N/A",
      "lastYearEPS": "$0.41",
      "time": "time-not-supplied",
      "symbol": "FINV",
      "name": "FinVolution Group",
      "marketCap": "$1,171,026,250",
      "fiscalQuarterEnding": "Mar/2026",
      "epsForecast": "",
      "noOfEsts": "1"
    },
    {
      "lastYearRptDt": "5/20/2025",
      "lastYearEPS": "$0.04",
      "time": "time-not-supplied",
      "symbol": "RERE",
      "name": "ATRenew Inc.",
      "marketCap": "$988,885,132",
      "fiscalQuarterEnding": "Mar/2026",
      "epsForecast": "$0.06",
      "noOfEsts": "1"
    },
    {
      "lastYearRptDt": "N/A",
      "lastYearEPS": "$32.43",
      "time": "time-not-supplied",
      "symbol": "DJCO",
      "name": "Daily Journal Corp. (S.C.)",
      "marketCap": "$728,484,285",
      "fiscalQuarterEnding": "Mar/2026",
      "epsForecast": "",
      "noOfEsts": "1"
    },
    {
      "lastYearRptDt": "N/A",
      "lastYearEPS": "$2.43",
      "time": "time-not-supplied",
      "symbol": "HOV",
      "name": "Hovnanian Enterprises Inc",
      "marketCap": "$667,690,533",
      "fiscalQuarterEnding": "Apr/2026",
      "epsForecast": "",
      "noOfEsts": "1"
    },
    {
      "lastYearRptDt": "N/A",
      "lastYearEPS": "($0.12)",
      "time": "time-not-supplied",
      "symbol": "ASPI",
      "name": "ASP Isotopes Inc.",
      "marketCap": "$662,252,131",
      "fiscalQuarterEnding": "Mar/2026",
      "epsForecast": "",
      "noOfEsts": "N/A"
    },
    {
      "lastYearRptDt": "N/A",
      "lastYearEPS": "($0.06)",
      "time": "time-not-supplied",
      "symbol": "ZKH",
      "name": "ZKH Group Limited",
      "marketCap": "$484,703,917",
      "fiscalQuarterEnding": "Mar/2026",
      "epsForecast": "",
      "noOfEsts": "1"
    },
    {
      "lastYearRptDt": "5/20/2025",
      "lastYearEPS": "($0.27)",
      "time": "time-not-supplied",
      "symbol": "CAN",
      "name": "Canaan Inc.",
      "marketCap": "$410,547,909",
      "fiscalQuarterEnding": "Mar/2026",
      "epsForecast": "($0.07)",
      "noOfEsts": "1"
    },
    {
      "lastYearRptDt": "5/20/2025",
      "lastYearEPS": "$0.19",
      "time": "time-after-hours",
      "symbol": "AUNA",
      "name": "Auna SA",
      "marketCap": "$375,245,733",
      "fiscalQuarterEnding": "Mar/2026",
      "epsForecast": "$0.19",
      "noOfEsts": "2"
    },
    {
      "lastYearRptDt": "5/20/2025",
      "lastYearEPS": "$0.22",
      "time": "time-not-supplied",
      "symbol": "KNOP",
      "name": "KNOT Offshore Partners LP",
      "marketCap": "$362,858,487",
      "fiscalQuarterEnding": "Mar/2026",
      "epsForecast": "$0.17",
      "noOfEsts": "1"
    },
    {
      "lastYearRptDt": "5/20/2025",
      "lastYearEPS": "($0.25)",
      "time": "time-not-supplied",
      "symbol": "GLSI",
      "name": "Greenwich LifeSciences, Inc.",
      "marketCap": "$327,244,211",
      "fiscalQuarterEnding": "Mar/2026",
      "epsForecast": "($0.33)",
      "noOfEsts": "2"
    },
    {
      "lastYearRptDt": "N/A",
      "lastYearEPS": "($0.13)",
      "time": "time-not-supplied",
      "symbol": "CURR",
      "name": "Currenc Group Inc.",
      "marketCap": "$272,736,741",
      "fiscalQuarterEnding": "Mar/2026",
      "epsForecast": "",
      "noOfEsts": "1"
    },
    {
      "lastYearRptDt": "5/19/2025",
      "lastYearEPS": "$0.02",
      "time": "time-after-hours",
      "symbol": "EGHT",
      "name": "8x8 Inc",
      "marketCap": "$267,491,232",
      "fiscalQuarterEnding": "Mar/2026",
      "epsForecast": "$0.03",
      "noOfEsts": "1"
    },
    {
      "lastYearRptDt": "5/07/2025",
      "lastYearEPS": "$0.02",
      "time": "time-pre-market",
      "symbol": "CRNT",
      "name": "Ceragon Networks Ltd.",
      "marketCap": "$228,101,157",
      "fiscalQuarterEnding": "Mar/2026",
      "epsForecast": "$0",
      "noOfEsts": "2"
    },
    {
      "lastYearRptDt": "5/20/2025",
      "lastYearEPS": "$0.26",
      "time": "time-not-supplied",
      "symbol": "EARN",
      "name": "Ellington Credit Company",
      "marketCap": "$177,279,400",
      "fiscalQuarterEnding": "Mar/2026",
      "epsForecast": "$0.22",
      "noOfEsts": "1"
    },
    {
      "lastYearRptDt": "N/A",
      "lastYearEPS": "N/A",
      "time": "time-not-supplied",
      "symbol": "VWAV",
      "name": "VisionWave Holdings, Inc.",
      "marketCap": "$149,760,020",
      "fiscalQuarterEnding": "Mar/2026",
      "epsForecast": "",
      "noOfEsts": "N/A"
    },
    {
      "lastYearRptDt": "N/A",
      "lastYearEPS": "($0.10)",
      "time": "time-not-supplied",
      "symbol": "DOYU",
      "name": "DouYu International Holdings Limited",
      "marketCap": "$147,272,832",
      "fiscalQuarterEnding": "Mar/2026",
      "epsForecast": "",
      "noOfEsts": "N/A"
    },
    {
      "lastYearRptDt": "N/A",
      "lastYearEPS": "($1.38)",
      "time": "time-not-supplied",
      "symbol": "CITR",
      "name": "CitroTech Inc.",
      "marketCap": "$123,710,512",
      "fiscalQuarterEnding": "Mar/2026",
      "epsForecast": "",
      "noOfEsts": "N/A"
    },
    {
      "lastYearRptDt": "N/A",
      "lastYearEPS": "N/A",
      "time": "time-not-supplied",
      "symbol": "QMCO",
      "name": "Quantum Corporation",
      "marketCap": "$104,515,527",
      "fiscalQuarterEnding": "Mar/2026",
      "epsForecast": "($0.37)",
      "noOfEsts": "1"
    },
    {
      "lastYearRptDt": "5/20/2025",
      "lastYearEPS": "($0.09)",
      "time": "time-not-supplied",
      "symbol": "CRGO",
      "name": "Freightos Limited",
      "marketCap": "$103,366,996",
      "fiscalQuarterEnding": "Mar/2026",
      "epsForecast": "($0.09)",
      "noOfEsts": "1"
    },
    {
      "lastYearRptDt": "5/20/2025",
      "lastYearEPS": "($0.12)",
      "time": "time-not-supplied",
      "symbol": "ARBE",
      "name": "Arbe Robotics Ltd.",
      "marketCap": "$93,355,836",
      "fiscalQuarterEnding": "Mar/2026",
      "epsForecast": "($0.10)",
      "noOfEsts": "1"
    },
    {
      "lastYearRptDt": "N/A",
      "lastYearEPS": "($0.12)",
      "time": "time-not-supplied",
      "symbol": "MDIA",
      "name": "Mediaco Holding Inc.",
      "marketCap": "$72,986,525",
      "fiscalQuarterEnding": "Mar/2026",
      "epsForecast": "",
      "noOfEsts": "1"
    },
    {
      "lastYearRptDt": "N/A",
      "lastYearEPS": "$0.15",
      "time": "time-not-supplied",
      "symbol": "ELTK",
      "name": "Eltek Ltd.",
      "marketCap": "$59,141,197",
      "fiscalQuarterEnding": "Mar/2026",
      "epsForecast": "",
      "noOfEsts": "1"
    },
    {
      "lastYearRptDt": "5/20/2025",
      "lastYearEPS": "($1.60)",
      "time": "time-not-supplied",
      "symbol": "NXXT",
      "name": "NextNRG, Inc.",
      "marketCap": "$58,009,337",
      "fiscalQuarterEnding": "Mar/2026",
      "epsForecast": "($0.08)",
      "noOfEsts": "1"
    },
    {
      "lastYearRptDt": "N/A",
      "lastYearEPS": "$0.45",
      "time": "time-not-supplied",
      "symbol": "BURU",
      "name": "Nuburu, Inc.",
      "marketCap": "$54,239,225",
      "fiscalQuarterEnding": "Mar/2026",
      "epsForecast": "",
      "noOfEsts": "N/A"
    },
    {
      "lastYearRptDt": "N/A",
      "lastYearEPS": "($0.05)",
      "time": "time-not-supplied",
      "symbol": "MAMO",
      "name": "Massimo Group",
      "marketCap": "$42,473,769",
      "fiscalQuarterEnding": "Mar/2026",
      "epsForecast": "",
      "noOfEsts": "N/A"
    },
    {
      "lastYearRptDt": "5/20/2025",
      "lastYearEPS": "$0.27",
      "time": "time-after-hours",
      "symbol": "CCIF",
      "name": "Carlyle Credit Income Fund",
      "marketCap": "$39,064,883",
      "fiscalQuarterEnding": "Mar/2026",
      "epsForecast": "$0.15",
      "noOfEsts": "2"
    },
    {
      "lastYearRptDt": "N/A",
      "lastYearEPS": "$3.04",
      "time": "time-not-supplied",
      "symbol": "STI",
      "name": "Solidion Technology, Inc.",
      "marketCap": "$37,876,390",
      "fiscalQuarterEnding": "Mar/2026",
      "epsForecast": "",
      "noOfEsts": "N/A"
    },
    {
      "lastYearRptDt": "N/A",
      "lastYearEPS": "($0.20)",
      "time": "time-not-supplied",
      "symbol": "BRLS",
      "name": "Borealis Foods Inc.",
      "marketCap": "$35,629,088",
      "fiscalQuarterEnding": "Mar/2026",
      "epsForecast": "",
      "noOfEsts": "1"
    },
    {
      "lastYearRptDt": "5/20/2025",
      "lastYearEPS": "$6.55",
      "time": "time-not-supplied",
      "symbol": "NEUP",
      "name": "Neuphoria Therapeutics Inc.",
      "marketCap": "$28,410,017",
      "fiscalQuarterEnding": "Mar/2026",
      "epsForecast": "($0.56)",
      "noOfEsts": "1"
    },
    {
      "lastYearRptDt": "N/A",
      "lastYearEPS": "$0.12",
      "time": "time-not-supplied",
      "symbol": "VEEA",
      "name": "Veea Inc.",
      "marketCap": "$25,707,859",
      "fiscalQuarterEnding": "Mar/2026",
      "epsForecast": "",
      "noOfEsts": "N/A"
    },
    {
      "lastYearRptDt": "N/A",
      "lastYearEPS": "($1.80)",
      "time": "time-not-supplied",
      "symbol": "EVTV",
      "name": "Envirotech Vehicles, Inc.",
      "marketCap": "$23,404,601",
      "fiscalQuarterEnding": "Mar/2026",
      "epsForecast": "",
      "noOfEsts": "N/A"
    },
    {
      "lastYearRptDt": "N/A",
      "lastYearEPS": "($1.04)",
      "time": "time-not-supplied",
      "symbol": "OSRH",
      "name": "OSR Holdings, Inc.",
      "marketCap": "$23,283,390",
      "fiscalQuarterEnding": "Mar/2026",
      "epsForecast": "",
      "noOfEsts": "N/A"
    },
    {
      "lastYearRptDt": "N/A",
      "lastYearEPS": "($0.47)",
      "time": "time-not-supplied",
      "symbol": "REBN",
      "name": "Reborn Coffee, Inc.",
      "marketCap": "$20,287,234",
      "fiscalQuarterEnding": "Mar/2026",
      "epsForecast": "",
      "noOfEsts": "N/A"
    },
    {
      "lastYearRptDt": "N/A",
      "lastYearEPS": "($0.30)",
      "time": "time-not-supplied",
      "symbol": "NIXX",
      "name": "Nixxy, Inc.",
      "marketCap": "$16,140,834",
      "fiscalQuarterEnding": "Mar/2026",
      "epsForecast": "",
      "noOfEsts": "N/A"
    },
    {
      "lastYearRptDt": "N/A",
      "lastYearEPS": "$75.92",
      "time": "time-not-supplied",
      "symbol": "HIND",
      "name": "Vyome Holdings, Inc.",
      "marketCap": "$14,247,612",
      "fiscalQuarterEnding": "Mar/2026",
      "epsForecast": "",
      "noOfEsts": "N/A"
    },
    {
      "lastYearRptDt": "N/A",
      "lastYearEPS": "($0.08)",
      "time": "time-not-supplied",
      "symbol": "CXAI",
      "name": "CXApp Inc.",
      "marketCap": "$11,318,531",
      "fiscalQuarterEnding": "Mar/2026",
      "epsForecast": "",
      "noOfEsts": "N/A"
    },
    {
      "lastYearRptDt": "N/A",
      "lastYearEPS": "($0.20)",
      "time": "time-not-supplied",
      "symbol": "GITS",
      "name": "Global Interactive Technologies, Inc. Common Stock",
      "marketCap": "$10,603,710",
      "fiscalQuarterEnding": "Mar/2026",
      "epsForecast": "",
      "noOfEsts": "N/A"
    },
    {
      "lastYearRptDt": "N/A",
      "lastYearEPS": "$1",
      "time": "time-not-supplied",
      "symbol": "XWEL",
      "name": "XWELL, Inc.",
      "marketCap": "$9,353,584",
      "fiscalQuarterEnding": "Mar/2026",
      "epsForecast": "",
      "noOfEsts": "1"
    },
    {
      "lastYearRptDt": "N/A",
      "lastYearEPS": "($0.15)",
      "time": "time-not-supplied",
      "symbol": "CETY",
      "name": "Clean Energy Technologies, Inc.",
      "marketCap": "$8,623,336",
      "fiscalQuarterEnding": "Mar/2026",
      "epsForecast": "",
      "noOfEsts": "1"
    },
    {
      "lastYearRptDt": "N/A",
      "lastYearEPS": "($50.60)",
      "time": "time-not-supplied",
      "symbol": "FTFT",
      "name": "Future FinTech Group Inc.",
      "marketCap": "$7,860,816",
      "fiscalQuarterEnding": "Mar/2026",
      "epsForecast": "",
      "noOfEsts": "N/A"
    },
    {
      "lastYearRptDt": "N/A",
      "lastYearEPS": "($10.14)",
      "time": "time-not-supplied",
      "symbol": "RVYL",
      "name": "Ryvyl Inc.",
      "marketCap": "$7,768,174",
      "fiscalQuarterEnding": "Mar/2026",
      "epsForecast": "",
      "noOfEsts": "N/A"
    },
    {
      "lastYearRptDt": "N/A",
      "lastYearEPS": "($0.20)",
      "time": "time-not-supplied",
      "symbol": "YHGJ",
      "name": "Yunhong Green CTI Ltd.",
      "marketCap": "$7,038,854",
      "fiscalQuarterEnding": "Mar/2026",
      "epsForecast": "",
      "noOfEsts": "N/A"
    },
    {
      "lastYearRptDt": "5/20/2025",
      "lastYearEPS": "($2.99)",
      "time": "time-not-supplied",
      "symbol": "AMZE",
      "name": "Amaze Holdings, Inc.",
      "marketCap": "$6,616,088",
      "fiscalQuarterEnding": "Mar/2026",
      "epsForecast": "",
      "noOfEsts": "N/A"
    },
    {
      "lastYearRptDt": "N/A",
      "lastYearEPS": "($2.70)",
      "time": "time-not-supplied",
      "symbol": "XHLD",
      "name": "TEN Holdings, Inc.",
      "marketCap": "$5,687,743",
      "fiscalQuarterEnding": "Mar/2026",
      "epsForecast": "",
      "noOfEsts": "1"
    },
    {
      "lastYearRptDt": "5/20/2025",
      "lastYearEPS": "($0.44)",
      "time": "time-not-supplied",
      "symbol": "SOPA",
      "name": "Society Pass Incorporated",
      "marketCap": "$5,039,089",
      "fiscalQuarterEnding": "Mar/2026",
      "epsForecast": "($0.11)",
      "noOfEsts": "2"
    },
    {
      "lastYearRptDt": "N/A",
      "lastYearEPS": "$34",
      "time": "time-not-supplied",
      "symbol": "VIVK",
      "name": "Vivakor, Inc.",
      "marketCap": "$4,570,371",
      "fiscalQuarterEnding": "Mar/2026",
      "epsForecast": "",
      "noOfEsts": "1"
    },
    {
      "lastYearRptDt": "5/20/2025",
      "lastYearEPS": "($99.99)",
      "time": "time-not-supplied",
      "symbol": "HCTI",
      "name": "Healthcare Triangle, Inc.",
      "marketCap": "$4,466,425",
      "fiscalQuarterEnding": "Mar/2026",
      "epsForecast": "",
      "noOfEsts": "N/A"
    },
    {
      "lastYearRptDt": "N/A",
      "lastYearEPS": "($39.80)",
      "time": "time-not-supplied",
      "symbol": "FEED",
      "name": "ENvue Medical, Inc.",
      "marketCap": "$4,293,053",
      "fiscalQuarterEnding": "Mar/2026",
      "epsForecast": "",
      "noOfEsts": "N/A"
    },
    {
      "lastYearRptDt": "N/A",
      "lastYearEPS": "($0.11)",
      "time": "time-not-supplied",
      "symbol": "SHFS",
      "name": "SHF Holdings, Inc.",
      "marketCap": "$3,560,235",
      "fiscalQuarterEnding": "Mar/2026",
      "epsForecast": "",
      "noOfEsts": "1"
    },
    {
      "lastYearRptDt": "5/20/2025",
      "lastYearEPS": "($99.99)",
      "time": "time-not-supplied",
      "symbol": "IPST",
      "name": "IP Strategy Holdings, Inc.",
      "marketCap": "$2,944,921",
      "fiscalQuarterEnding": "Mar/2026",
      "epsForecast": "$0.60",
      "noOfEsts": "1"
    },
    {
      "lastYearRptDt": "N/A",
      "lastYearEPS": "($99.99)",
      "time": "time-not-supplied",
      "symbol": "IVF",
      "name": "INVO Fertility, Inc.",
      "marketCap": "$2,617,372",
      "fiscalQuarterEnding": "Mar/2026",
      "epsForecast": "",
      "noOfEsts": "N/A"
    },
    {
      "lastYearRptDt": "N/A",
      "lastYearEPS": "($0.23)",
      "time": "time-not-supplied",
      "symbol": "CNET",
      "name": "ZW Data Action Technologies Inc.",
      "marketCap": "$2,418,637",
      "fiscalQuarterEnding": "Mar/2026",
      "epsForecast": "",
      "noOfEsts": "N/A"
    },
    {
      "lastYearRptDt": "N/A",
      "lastYearEPS": "N/A",
      "time": "time-not-supplied",
      "symbol": "KUST",
      "name": "Kustom Entertainment, Inc.",
      "marketCap": "$1,769,420",
      "fiscalQuarterEnding": "Mar/2026",
      "epsForecast": "",
      "noOfEsts": "N/A"
    },
    {
      "lastYearRptDt": "N/A",
      "lastYearEPS": "$0.90",
      "time": "time-not-supplied",
      "symbol": "SSM",
      "name": "Sono Group N.V.",
      "marketCap": "",
      "fiscalQuarterEnding": "Mar/2026",
      "epsForecast": "",
      "noOfEsts": "1"
    }
  ]
}